greatlibrarian/__init__.py
greatlibrarian/Agents/__init__.py
greatlibrarian/Agents/BookStore/__init__.py
greatlibrarian/Agents/BookStore/checkDupli.py
greatlibrarian/Agents/BookStore/getData.py
greatlibrarian/Agents/BookStore/main.py
greatlibrarian/Agents/BookStore/RawData/Area Studies/African American Studies.csv
greatlibrarian/Agents/CodeRunner/__init__.py
greatlibrarian/Agents/CodeRunner/codeComphnExp.py
greatlibrarian/Agents/CodeRunner/codeDefeIdentify.py
greatlibrarian/Agents/CodeRunner/codeEnv.py
greatlibrarian/Agents/CodeRunner/codeOpt.py
greatlibrarian/Agents/CodeRunner/test_code.json
greatlibrarian/Agents/CodeRunner/ttest.py
greatlibrarian/Agents/CodeRunner/VirEnv/bin/activate
greatlibrarian/Agents/CodeRunner/VirEnv/bin/activate.csh
greatlibrarian/Agents/CodeRunner/VirEnv/bin/activate.fish
greatlibrarian/Agents/CodeRunner/VirEnv/bin/Activate.ps1
greatlibrarian/Agents/CodeRunner/VirEnv/bin/pip
greatlibrarian/Agents/CodeRunner/VirEnv/bin/pip3
greatlibrarian/Agents/CodeRunner/VirEnv/bin/pip3.8
greatlibrarian/Agents/CodeRunner/VirEnv/bin/python
greatlibrarian/Agents/CodeRunner/VirEnv/bin/python3
greatlibrarian/Agents/CodeRunner/VirEnv/lib/python3.8/site-packages/_distutils_hack/__init__.py
greatlibrarian/Agents/CodeRunner/VirEnv/lib/python3.8/site-packages/_distutils_hack/override.py
greatlibrarian/Agents/CodeRunner/VirEnv/lib/python3.8/site-packages/distutils-precedence.pth
greatlibrarian/Agents/CodeRunner/VirEnv/lib/python3.8/site-packages/pip/__init__.py
greatlibrarian/Agents/CodeRunner/VirEnv/lib/python3.8/site-packages/pip/__main__.py
greatlibrarian/Agents/CodeRunner/VirEnv/lib/python3.8/site-packages/pip/__pip-runner__.py
greatlibrarian/Agents/CodeRunner/VirEnv/lib/python3.8/site-packages/pip/_internal/__init__.py
greatlibrarian/Agents/CodeRunner/VirEnv/lib/python3.8/site-packages/pip/_internal/build_env.py
greatlibrarian/Agents/CodeRunner/VirEnv/lib/python3.8/site-packages/pip/_internal/cache.py
greatlibrarian/Agents/CodeRunner/VirEnv/lib/python3.8/site-packages/pip-23.0.1.dist-info/entry_points.txt
greatlibrarian/Agents/CodeRunner/VirEnv/lib/python3.8/site-packages/pip-23.0.1.dist-info/INSTALLER
greatlibrarian/Agents/CodeRunner/VirEnv/lib/python3.8/site-packages/pip-23.0.1.dist-info/LICENSE.txt
greatlibrarian/Agents/CodeRunner/VirEnv/lib/python3.8/site-packages/pip-23.0.1.dist-info/METADATA
greatlibrarian/Agents/CodeRunner/VirEnv/lib/python3.8/site-packages/pip-23.0.1.dist-info/RECORD
greatlibrarian/Agents/CodeRunner/VirEnv/lib/python3.8/site-packages/pip-23.0.1.dist-info/REQUESTED
greatlibrarian/Agents/CodeRunner/VirEnv/lib/python3.8/site-packages/pip-23.0.1.dist-info/top_level.txt
greatlibrarian/Agents/CodeRunner/VirEnv/lib/python3.8/site-packages/pip-23.0.1.dist-info/WHEEL
greatlibrarian/Agents/CodeRunner/VirEnv/lib/python3.8/site-packages/setuptools-56.0.0.dist-info/dependency_links.txt
greatlibrarian/Agents/CodeRunner/VirEnv/lib/python3.8/site-packages/setuptools-56.0.0.dist-info/entry_points.txt
greatlibrarian/Agents/CodeRunner/VirEnv/lib/python3.8/site-packages/setuptools-56.0.0.dist-info/INSTALLER
greatlibrarian/Agents/CodeRunner/VirEnv/lib/python3.8/site-packages/setuptools-56.0.0.dist-info/LICENSE
greatlibrarian/Agents/CodeRunner/VirEnv/lib/python3.8/site-packages/setuptools-56.0.0.dist-info/METADATA
greatlibrarian/Agents/CodeRunner/VirEnv/lib/python3.8/site-packages/setuptools-56.0.0.dist-info/RECORD
greatlibrarian/Agents/CodeRunner/VirEnv/lib/python3.8/site-packages/setuptools-56.0.0.dist-info/REQUESTED
greatlibrarian/Agents/CodeRunner/VirEnv/lib/python3.8/site-packages/setuptools-56.0.0.dist-info/top_level.txt
greatlibrarian/Agents/CodeRunner/VirEnv/lib/python3.8/site-packages/setuptools-56.0.0.dist-info/WHEEL
greatlibrarian-0.1.9.dist-info/entry_points.txt
greatlibrarian-0.1.9.dist-info/METADATA
greatlibrarian-0.1.9.dist-info/WHEEL
greatlibrarian-0.1.9.dist-info/RECORD
